{
  "$schema": "https://mintlify.com/docs.json",
  "theme": "mint",
  "name": "Qubit Alpha",
  "colors": {
  "primary": "#2961FF",
  "light": "#2961FF",
  "dark": "#2961FF"
},
  "favicon": "/favicon.svg",
 "navigation": {
  "tabs": [
    {
      "tab": "English",
      "groups": [
        {
          "group": "Introduction",
          "icon": "book-open",
          "pages": [
            {
              "page": "introduction/what-is-qubit-alpha",
              "icon": "circle-info"
            },
            {
              "page": "introduction/why-qubit-alpha",
              "icon": "lightbulb"
            },
            {
              "page": "introduction/who-is-qubit-alpha-for",
              "icon": "users"
            }
          ]
        },
        {
          "group": "Our Advantages",
          "icon": "star",
          "pages": [
            {
              "page": "advantages/speed-execution",
              "icon": "bolt"
            },
            {
              "page": "advantages/non-custodial",
              "icon": "shield"
            },
            {
              "page": "advantages/risk-management",
              "icon": "shield-halved"
            },
            {
              "page": "advantages/transparency",
              "icon": "eye"
            }
          ]
        },
        {
          "group": "User Guide",
          "icon": "map",
          "pages": [
            {
              "page": "guide/concepts",
              "icon": "list"
            },
            {
              "page": "guide/quick-start",
              "icon": "rocket"
            },
            {
              "page": "guide/asset-management",
              "icon": "wallet"
            },
            {
              "page": "guide/copy-trading",
              "icon": "copy"
            },
            {
              "page": "guide/dashboard",
              "icon": "chart-line"
            },
            {
              "page": "guide/owner-guide",
              "icon": "user-gear"
            },
            {
              "page": "guide/referral",
              "icon": "users"
            }
          ]
        },
        {
          "group": "FAQ",
          "icon": "circle-question",
          "pages": [
            {
              "page": "faq/fees",
              "icon": "receipt"
            },
            {
              "page": "faq/security",
              "icon": "triangle-exclamation"
            },
            {
              "page": "faq/troubleshooting",
              "icon": "wrench"
            },
            {
              "page": "faq/community",
              "icon": "users"
            }
          ]
        },
        {
          "group": "Updates",
          "icon": "sparkles",
          "pages": [
            {
              "page": "changelog",
              "icon": "list"
            }
          ]
        },
        {
          "group": "Community",
          "icon": "folder",
          "pages": [
            {
              "page": "brand-kit",
              "icon": "palette"
            }
          ]
        },
        {
          "group": "Legal",
          "icon": "shield",
          "pages": [
            {
              "page": "legal/terms-of-service",
              "icon": "file-lines"
            },
            {
              "page": "legal/privacy-policy",
              "icon": "shield-check"
            }
          ]
        }
      ]
    },
    {
      "tab": "中文",
      "groups": [
        {
          "group": "介绍",
          "pages": [
            "zh/introduction/what-is-qubit-alpha",
            "zh/introduction/why-qubit-alpha",
            "zh/introduction/who-is-qubit-alpha-for"
          ]
        }
      ]
    }
  ]
}
  "topbarLinks": [
    {
      "name": "Support",
      "url": "https://t.me/QuBitDEX"
    }
  ],
  "topbarCtaButton": {
    "name": "Launch App",
    "url": "https://alpha.qubit.trade"
  },
  "anchors": [
    {
      "name": "App",
      "icon": "rocket",
      "url": "https://alpha.qubit.trade"
    },
    {
      "name": "Telegram",
      "icon": "telegram",
      "url": "https://t.me/QuBitDEX"
    }
  ],
  "footerSocials": {
    "x": "https://x.com/QuBitDEX",
    "telegram": "https://t.me/QuBitDEX"
  }
}